process_runner_start/__init__.py
process_runner_start/main.py
process_runner_start-1.0.3.dist-info/LICENSE
process_runner_start-1.0.3.dist-info/METADATA
process_runner_start-1.0.3.dist-info/WHEEL
process_runner_start-1.0.3.dist-info/entry_points.txt
process_runner_start-1.0.3.dist-info/top_level.txt
process_runner_start-1.0.3.dist-info/RECORD
