Metadata-Version: 2.1
Name: process-runner_start
Version: 1.0.3
Summary: A command-line tool to simplify running and compiling projects.
Home-page: https://github.com/Exator921/process-runner
Author: Exator911
Author-email: matthewbates0727@gmail.com
Classifier: Programming Language :: Python :: 3
Classifier: License :: OSI Approved :: MIT License
Classifier: Operating System :: OS Independent
Requires-Python: >=3.6
License-File: LICENSE
